<?xml version="1.0" encoding="UTF-8" ?>
<language>
	<page id="1044">
		<t id="101">Reassign employee</t>
		<t id="102">Select ship</t>
		<t id="103">One of the ships must have a free slot</t>
		<t id="104">More...</t>
		<t id="105">Back</t>
		<t id="106">Reassigned</t>
		<t id="107">(Current location)</t>
		<t id="108">Captain</t>
		<t id="109">Manager</t>
		<t id="110">Service Crew</t>
		<t id="111">Marine</t>
		<t id="112">Mass move crew</t>
		<t id="113">Mass move best Service Crew</t>
		<t id="114">Mass move worst Service Crew</t>
		<t id="115">Mass move best Marines</t>
		<t id="116">Mass move worst Marines</t>
	</page>
</language>